[
{
    "device_IP": "172.16.1.12",
    "clusterName": "",
    "discover_ADC": "USE_BIGIQ",
    "discover_ASM": "USE_BIGIP",
    "discover_AFM": "USE_BIGIP",
    "discover_APM": "false",
    "discover_DNS": "none"
},
{
    "device_IP": "172.16.1.21",
    "clusterName": "pair",
    "accessGroup": "MyAccessGroup",
    "discover_ADC": "USE_BIGIQ",
    "discover_ASM": "USE_BIGIP",
    "discover_AFM": "false",
    "discover_APM": "USE_BIGIP",
    "discover_DNS": "false",
    "BIG-IP_username": "admin",
    "BIG-IP_password": "admin",
    "BIG-IP_root_password": "default"
},
{
    "device_IP": "172.16.1.22",
    "clusterName": "pair",
    "accessGroup": "MyAccessGroup",
    "discover_ADC": "USE_BIGIQ",
    "discover_ASM": "USE_BIGIP",
    "discover_AFM": "false",
    "discover_APM": "USE_BIGIP",
    "discover_DNS": "false",
    "BIG-IP_username": "admin",
    "BIG-IP_password": "admin",
    "BIG-IP_root_password": "default"
}
]
